{
  "site": {
    "name": "مركز الفوزان",
    "logo": "",
    "registerUrl": "https://docs.google.com/forms/d/e/your-form-id/viewform"
  },
  "texts": {
    "hero.title": "مركز الفوزان لتحفيظ القرآن الكريم",
    "hero.lead": "بيت يجمع القلوب على كتاب الله، يرعى الناشئة بالتلاوة والحفظ والتجويد، ويغرس فيهم محبة القرآن وأخلاقه.",
    "stats.students": "+196",
    "stats.teachers": "+13",
    "stats.years": "+12",
    "about.title": "لمحة عنّا",
    "about.paragraph1": "مركز الفوزان مركز قرآني يُعنى بتحفيظ كتاب الله العزيز وفق منهجٍ متدرّج، بإشراف نخبة من المعلمين المجازين. نسعى لبناء جيلٍ يحبّ القرآن ويعيش معانيه.",
    "about.paragraph2": "نُقدّم حلقاتٍ مخصصة لمختلف المراحل (ابتدائي، متوسط، ثانوي) في بيئة هادئة تشجع على التركيز والإتقان، مع متابعة دقيقة لتقدم الطالب أسبوعياً.",
    "about.feature1": "حلقات على يد معلمين مجازين بالسند",
    "about.feature2": "متابعة أسبوعية للحضور والحفظ",
    "about.feature3": "مسابقات وتكريم للطلاب المتميزين",
    "about.feature4": "بيئة آمنة ومحفّزة للتعلم",
    "register.title": "سجّل في حلقات الفوزان",
    "register.text": "يسرّنا انضمامك إلى أسرة المركز. اضغط على الزر التالي لفتح نموذج التسجيل وملء بياناتك."
  },
  "aboutMedia": [],
  "achievements": [],
  "activities": [],
  "halaqat": [
    {"id":"h01","name":"حلقة الإمام الإتقان","level":"ثانوي","targetGrade":"ثانوي","sheikh":""},
    {"id":"h02","name":"الحلقة الرائدة","level":"ثانوي","targetGrade":"ثانوي","sheikh":""},
    {"id":"h03","name":"حلقة الإمام ابن تيمية","level":"ثانوي","targetGrade":"الثانوي","sheikh":""},
    {"id":"h04","name":"حلقة الإمام أبي حنيفة","level":"ثانوي","targetGrade":"الثانوي","sheikh":""},
    {"id":"h05","name":"حلقة الإمام أحمد بن حنبل","level":"متوسط","targetGrade":"الثالث المتوسط","sheikh":""},
    {"id":"h06","name":"حلقة الإمام علي ابن المديني","level":"متوسط","targetGrade":"الثاني المتوسط","sheikh":""},
    {"id":"h07","name":"حلقة الإمام الشافعي","level":"متوسط","targetGrade":"الأول المتوسط","sheikh":""},
    {"id":"h08","name":"حلقة الإمام البخاري","level":"ابتدائي","targetGrade":"السادس الابتدائي","sheikh":""},
    {"id":"h09","name":"حلقة الإمام الترمذي","level":"ابتدائي","targetGrade":"الخامس الابتدائي","sheikh":""},
    {"id":"h10","name":"حلقة الإمام الشعبي","level":"ابتدائي","targetGrade":"الرابع الابتدائي","sheikh":""},
    {"id":"h11","name":"حلقة الإمام أبو داوود","level":"ابتدائي","targetGrade":"الثالث الابتدائي","sheikh":""},
    {"id":"h12","name":"حلقة الإمام ابن القيم","level":"ابتدائي","targetGrade":"الثاني الابتدائي","sheikh":""},
    {"id":"h13","name":"حلقة الإمام النسائي","level":"ابتدائي","targetGrade":"الأول الابتدائي","sheikh":""}
  ],
  "students": [
    {"id":"s001","serial":"001","name":"أحمد عصام","halaqaId":"h01","grade":"","attendance":{}},
    {"id":"s002","serial":"002","name":"أحمد ضياء","halaqaId":"h01","grade":"","attendance":{}},
    {"id":"s003","serial":"003","name":"أحمد أسامة","halaqaId":"h01","grade":"","attendance":{}},
    {"id":"s004","serial":"004","name":"مهند سيد","halaqaId":"h01","grade":"","attendance":{}},
    {"id":"s005","serial":"005","name":"إسلام حامد","halaqaId":"h01","grade":"","attendance":{}},
    {"id":"s006","serial":"006","name":"عبد الرحمن با حسين","halaqaId":"h01","grade":"","attendance":{}},
    {"id":"s007","serial":"007","name":"يوسف مجدي شندي","halaqaId":"h01","grade":"","attendance":{}},
    {"id":"s008","serial":"008","name":"أحمد علي","halaqaId":"h01","grade":"","attendance":{}},
    {"id":"s009","serial":"009","name":"إسماعيل بسام","halaqaId":"h02","grade":"","attendance":{}},
    {"id":"s010","serial":"010","name":"محمد ضياء","halaqaId":"h02","grade":"","attendance":{}},
    {"id":"s011","serial":"011","name":"حسن بركات","halaqaId":"h02","grade":"","attendance":{}},
    {"id":"s012","serial":"012","name":"منصور قاسم","halaqaId":"h02","grade":"","attendance":{}},
    {"id":"s013","serial":"013","name":"يوسف أحمد","halaqaId":"h02","grade":"","attendance":{}},
    {"id":"s014","serial":"014","name":"البراء محمد عاطف","halaqaId":"h02","grade":"","attendance":{}},
    {"id":"s015","serial":"015","name":"عمر رمضان","halaqaId":"h02","grade":"","attendance":{}},
    {"id":"s016","serial":"016","name":"محمود توفيق الشعيبي","halaqaId":"h03","grade":"","attendance":{}},
    {"id":"s017","serial":"017","name":"عمرو محمد علام","halaqaId":"h03","grade":"","attendance":{}},
    {"id":"s018","serial":"018","name":"محمد حامد شعبان","halaqaId":"h03","grade":"","attendance":{}},
    {"id":"s019","serial":"019","name":"فارس علي يحيى","halaqaId":"h03","grade":"","attendance":{}},
    {"id":"s020","serial":"020","name":"يوسف سامي محمد","halaqaId":"h03","grade":"","attendance":{}},
    {"id":"s021","serial":"021","name":"عبد الله وائل شاهين","halaqaId":"h03","grade":"","attendance":{}},
    {"id":"s022","serial":"022","name":"محمد معمر","halaqaId":"h03","grade":"","attendance":{}},
    {"id":"s023","serial":"023","name":"ناصر منصور","halaqaId":"h03","grade":"","attendance":{}},
    {"id":"s024","serial":"024","name":"مؤيد جمال","halaqaId":"h03","grade":"","attendance":{}},
    {"id":"s025","serial":"025","name":"خالد وليد البعداني","halaqaId":"h03","grade":"","attendance":{}},
    {"id":"s026","serial":"026","name":"يوسف أسامة","halaqaId":"h03","grade":"","attendance":{}},
    {"id":"s027","serial":"027","name":"خالد رأفت","halaqaId":"h03","grade":"","attendance":{}},
    {"id":"s028","serial":"028","name":"عبد الله محمد الطارقي","halaqaId":"h03","grade":"","attendance":{}},
    {"id":"s029","serial":"029","name":"إسماعيل عيسى","halaqaId":"h03","grade":"","attendance":{}},
    {"id":"s030","serial":"030","name":"عمرو عصام","halaqaId":"h03","grade":"","attendance":{}},
    {"id":"s031","serial":"031","name":"علي محمد علي","halaqaId":"h04","grade":"","attendance":{}},
    {"id":"s032","serial":"032","name":"معاذ محمد مبروك","halaqaId":"h04","grade":"","attendance":{}},
    {"id":"s033","serial":"033","name":"فهد علي الفتح","halaqaId":"h04","grade":"","attendance":{}},
    {"id":"s034","serial":"034","name":"عمر محمد أبكر","halaqaId":"h04","grade":"","attendance":{}},
    {"id":"s035","serial":"035","name":"زياد محمد إبراهيم","halaqaId":"h04","grade":"","attendance":{}},
    {"id":"s036","serial":"036","name":"مصطفى محمد طه","halaqaId":"h04","grade":"","attendance":{}},
    {"id":"s037","serial":"037","name":"ريان صالح شوبان","halaqaId":"h04","grade":"","attendance":{}},
    {"id":"s038","serial":"038","name":"ريان لهدان","halaqaId":"h04","grade":"","attendance":{}},
    {"id":"s039","serial":"039","name":"فارس محمد عبد الرحمن","halaqaId":"h04","grade":"","attendance":{}},
    {"id":"s040","serial":"040","name":"صالح أكرم الخراز","halaqaId":"h04","grade":"","attendance":{}},
    {"id":"s041","serial":"041","name":"توفيق مطهر","halaqaId":"h04","grade":"","attendance":{}},
    {"id":"s042","serial":"042","name":"أحمد هلال اليافعي","halaqaId":"h04","grade":"","attendance":{}},
    {"id":"s043","serial":"043","name":"عبد القادر صالح","halaqaId":"h04","grade":"","attendance":{}},
    {"id":"s044","serial":"044","name":"أمين علي محمد","halaqaId":"h04","grade":"","attendance":{}},
    {"id":"s045","serial":"045","name":"إبراهيم عيسى قوري","halaqaId":"h04","grade":"","attendance":{}},
    {"id":"s046","serial":"046","name":"أسامة محمد سعد","halaqaId":"h04","grade":"","attendance":{}},
    {"id":"s047","serial":"047","name":"مجدي طارق","halaqaId":"h04","grade":"","attendance":{}},
    {"id":"s048","serial":"048","name":"محمد أكرم الخراز","halaqaId":"h05","grade":"","attendance":{}},
    {"id":"s049","serial":"049","name":"عمر سامي محمد","halaqaId":"h05","grade":"","attendance":{}},
    {"id":"s050","serial":"050","name":"زياد محمد محمود","halaqaId":"h05","grade":"","attendance":{}},
    {"id":"s051","serial":"051","name":"كريم حامد عامر","halaqaId":"h05","grade":"","attendance":{}},
    {"id":"s052","serial":"052","name":"عبد الرحمن محمد قاعود","halaqaId":"h05","grade":"","attendance":{}},
    {"id":"s053","serial":"053","name":"فارس عبد الله القاضي","halaqaId":"h05","grade":"","attendance":{}},
    {"id":"s054","serial":"054","name":"أحمد محمد فيصل","halaqaId":"h05","grade":"","attendance":{}},
    {"id":"s055","serial":"055","name":"أنس القاضي","halaqaId":"h05","grade":"","attendance":{}},
    {"id":"s056","serial":"056","name":"مساعد قاسم الصهولي","halaqaId":"h05","grade":"","attendance":{}},
    {"id":"s057","serial":"057","name":"مشعل عبد القادر حدير","halaqaId":"h05","grade":"","attendance":{}},
    {"id":"s058","serial":"058","name":"إبراهيم النمر","halaqaId":"h05","grade":"","attendance":{}},
    {"id":"s059","serial":"059","name":"عبد الملك حسين","halaqaId":"h05","grade":"","attendance":{}},
    {"id":"s060","serial":"060","name":"صادق عبد القادر حدير","halaqaId":"h05","grade":"","attendance":{}},
    {"id":"s061","serial":"061","name":"سامح أسامة","halaqaId":"h05","grade":"","attendance":{}},
    {"id":"s062","serial":"062","name":"أسامة عبد الله راجح","halaqaId":"h05","grade":"","attendance":{}},
    {"id":"s063","serial":"063","name":"يزن عمر يوسف","halaqaId":"h05","grade":"","attendance":{}},
    {"id":"s064","serial":"064","name":"نهاد عمر الأهدل","halaqaId":"h05","grade":"","attendance":{}},
    {"id":"s065","serial":"065","name":"محمد علي","halaqaId":"h05","grade":"","attendance":{}},
    {"id":"s066","serial":"066","name":"عبد العزيز هدير","halaqaId":"h05","grade":"","attendance":{}},
    {"id":"s067","serial":"067","name":"متعب عبد العليم","halaqaId":"h06","grade":"","attendance":{}},
    {"id":"s068","serial":"068","name":"إياد محمد","halaqaId":"h06","grade":"","attendance":{}},
    {"id":"s069","serial":"069","name":"علي أحمد ندا","halaqaId":"h06","grade":"","attendance":{}},
    {"id":"s070","serial":"070","name":"سيف حمادة","halaqaId":"h06","grade":"","attendance":{}},
    {"id":"s071","serial":"071","name":"يوسف حمادة","halaqaId":"h06","grade":"","attendance":{}},
    {"id":"s072","serial":"072","name":"عبد الله عبد الرحمن","halaqaId":"h06","grade":"","attendance":{}},
    {"id":"s073","serial":"073","name":"علي محمد قحطان","halaqaId":"h06","grade":"","attendance":{}},
    {"id":"s074","serial":"074","name":"وزير علي","halaqaId":"h06","grade":"","attendance":{}},
    {"id":"s075","serial":"075","name":"مدثر بهاء","halaqaId":"h06","grade":"","attendance":{}},
    {"id":"s076","serial":"076","name":"فيصل محمد","halaqaId":"h06","grade":"","attendance":{}},
    {"id":"s077","serial":"077","name":"مختار عرفات","halaqaId":"h06","grade":"","attendance":{}},
    {"id":"s078","serial":"078","name":"محمد علي","halaqaId":"h06","grade":"","attendance":{}},
    {"id":"s079","serial":"079","name":"محمد وليد البعداني","halaqaId":"h06","grade":"","attendance":{}},
    {"id":"s080","serial":"080","name":"عبيد عثمان علي","halaqaId":"h06","grade":"","attendance":{}},
    {"id":"s081","serial":"081","name":"عبد الرحمن خالد محمد","halaqaId":"h06","grade":"","attendance":{}},
    {"id":"s082","serial":"082","name":"صالح عاتق","halaqaId":"h06","grade":"","attendance":{}},
    {"id":"s083","serial":"083","name":"مستور قاسم علي","halaqaId":"h07","grade":"","attendance":{}},
    {"id":"s084","serial":"084","name":"عبد الرحمن عبيد فياض","halaqaId":"h07","grade":"","attendance":{}},
    {"id":"s085","serial":"085","name":"حازم أحمد نصر","halaqaId":"h07","grade":"","attendance":{}},
    {"id":"s086","serial":"086","name":"باسم أحمد عبد العزيز","halaqaId":"h07","grade":"","attendance":{}},
    {"id":"s087","serial":"087","name":"إبراهيم محمد المحمدي","halaqaId":"h07","grade":"","attendance":{}},
    {"id":"s088","serial":"088","name":"فرات عيسى","halaqaId":"h07","grade":"","attendance":{}},
    {"id":"s089","serial":"089","name":"حسام عبد الله راجح","halaqaId":"h07","grade":"","attendance":{}},
    {"id":"s090","serial":"090","name":"مصطفى سالم","halaqaId":"h07","grade":"","attendance":{}},
    {"id":"s091","serial":"091","name":"عمر سعد حسين","halaqaId":"h07","grade":"","attendance":{}},
    {"id":"s092","serial":"092","name":"علاء موسى","halaqaId":"h07","grade":"","attendance":{}},
    {"id":"s093","serial":"093","name":"منتظر موسى","halaqaId":"h07","grade":"","attendance":{}},
    {"id":"s094","serial":"094","name":"محمد توفيق","halaqaId":"h07","grade":"","attendance":{}},
    {"id":"s095","serial":"095","name":"آدم محمد","halaqaId":"h07","grade":"","attendance":{}},
    {"id":"s096","serial":"096","name":"سيف محمد","halaqaId":"h07","grade":"","attendance":{}},
    {"id":"s097","serial":"097","name":"مصطفى محمود","halaqaId":"h07","grade":"","attendance":{}},
    {"id":"s098","serial":"098","name":"أحمد جميل أحمد","halaqaId":"h08","grade":"","attendance":{}},
    {"id":"s099","serial":"099","name":"عمار ياسر إبراهيم","halaqaId":"h08","grade":"","attendance":{}},
    {"id":"s100","serial":"100","name":"خالد محمود","halaqaId":"h08","grade":"","attendance":{}},
    {"id":"s101","serial":"101","name":"صالح يحيى محمد","halaqaId":"h08","grade":"","attendance":{}},
    {"id":"s102","serial":"102","name":"محمد باسم يوسف","halaqaId":"h08","grade":"","attendance":{}},
    {"id":"s103","serial":"103","name":"عبد الله علاء أبو بكر","halaqaId":"h08","grade":"","attendance":{}},
    {"id":"s104","serial":"104","name":"البراء وائل شاهين","halaqaId":"h08","grade":"","attendance":{}},
    {"id":"s105","serial":"105","name":"خالد موسى","halaqaId":"h08","grade":"","attendance":{}},
    {"id":"s106","serial":"106","name":"راشد صالح شوبان","halaqaId":"h08","grade":"","attendance":{}},
    {"id":"s107","serial":"107","name":"أحمد طارق","halaqaId":"h08","grade":"","attendance":{}},
    {"id":"s108","serial":"108","name":"محمد أمين","halaqaId":"h08","grade":"","attendance":{}},
    {"id":"s109","serial":"109","name":"محمد محمود الدخاخني","halaqaId":"h08","grade":"","attendance":{}},
    {"id":"s110","serial":"110","name":"يزيد أسعد","halaqaId":"h09","grade":"","attendance":{}},
    {"id":"s111","serial":"111","name":"مازن أحمد","halaqaId":"h09","grade":"","attendance":{}},
    {"id":"s112","serial":"112","name":"معاذ قاعود","halaqaId":"h09","grade":"","attendance":{}},
    {"id":"s113","serial":"113","name":"لؤي حامد","halaqaId":"h09","grade":"","attendance":{}},
    {"id":"s114","serial":"114","name":"أحمد تامر","halaqaId":"h09","grade":"","attendance":{}},
    {"id":"s115","serial":"115","name":"محمد مفيد","halaqaId":"h09","grade":"","attendance":{}},
    {"id":"s116","serial":"116","name":"أنور منصور","halaqaId":"h09","grade":"","attendance":{}},
    {"id":"s117","serial":"117","name":"علي أحمد السويري","halaqaId":"h09","grade":"","attendance":{}},
    {"id":"s118","serial":"118","name":"مالك ياسر","halaqaId":"h09","grade":"","attendance":{}},
    {"id":"s119","serial":"119","name":"محمد سالم","halaqaId":"h09","grade":"","attendance":{}},
    {"id":"s120","serial":"120","name":"أحمد محمد طه","halaqaId":"h09","grade":"","attendance":{}},
    {"id":"s121","serial":"121","name":"إبراهيم رأفت","halaqaId":"h09","grade":"","attendance":{}},
    {"id":"s122","serial":"122","name":"عبد الرحمن عبد الكريم","halaqaId":"h09","grade":"","attendance":{}},
    {"id":"s123","serial":"123","name":"عمر أسامة","halaqaId":"h09","grade":"","attendance":{}},
    {"id":"s124","serial":"124","name":"محمد حازم","halaqaId":"h10","grade":"","attendance":{}},
    {"id":"s125","serial":"125","name":"أنور عبدو","halaqaId":"h10","grade":"","attendance":{}},
    {"id":"s126","serial":"126","name":"عبيدة علاء","halaqaId":"h10","grade":"","attendance":{}},
    {"id":"s127","serial":"127","name":"كرم صابر","halaqaId":"h10","grade":"","attendance":{}},
    {"id":"s128","serial":"128","name":"إياد عماد","halaqaId":"h10","grade":"","attendance":{}},
    {"id":"s129","serial":"129","name":"قصي عبد الباسط","halaqaId":"h10","grade":"","attendance":{}},
    {"id":"s130","serial":"130","name":"عبد الرحمن أسامة","halaqaId":"h10","grade":"","attendance":{}},
    {"id":"s131","serial":"131","name":"محمد عبيد","halaqaId":"h10","grade":"","attendance":{}},
    {"id":"s132","serial":"132","name":"أنس أحمد","halaqaId":"h10","grade":"","attendance":{}},
    {"id":"s133","serial":"133","name":"عبد الرحمن رجب","halaqaId":"h10","grade":"","attendance":{}},
    {"id":"s134","serial":"134","name":"ياسين حمادة","halaqaId":"h10","grade":"","attendance":{}},
    {"id":"s135","serial":"135","name":"أحمد تيسير","halaqaId":"h10","grade":"","attendance":{}},
    {"id":"s136","serial":"136","name":"ياسين أحمد","halaqaId":"h10","grade":"","attendance":{}},
    {"id":"s137","serial":"137","name":"إبراهيم حسين","halaqaId":"h10","grade":"","attendance":{}},
    {"id":"s138","serial":"138","name":"حمزة حنفي","halaqaId":"h10","grade":"","attendance":{}},
    {"id":"s139","serial":"139","name":"محمد عنتر","halaqaId":"h10","grade":"","attendance":{}},
    {"id":"s140","serial":"140","name":"مُندي محمود","halaqaId":"h10","grade":"","attendance":{}},
    {"id":"s141","serial":"141","name":"عبد الله علي","halaqaId":"h10","grade":"","attendance":{}},
    {"id":"s142","serial":"142","name":"تميم مازن سامي","halaqaId":"h10","grade":"","attendance":{}},
    {"id":"s143","serial":"143","name":"إياد تيسير","halaqaId":"h11","grade":"","attendance":{}},
    {"id":"s144","serial":"144","name":"عبد الملك عبد الرحمن","halaqaId":"h11","grade":"","attendance":{}},
    {"id":"s145","serial":"145","name":"علي عبد الله القاضي","halaqaId":"h11","grade":"","attendance":{}},
    {"id":"s146","serial":"146","name":"أنس سامي صالح","halaqaId":"h11","grade":"","attendance":{}},
    {"id":"s147","serial":"147","name":"محمد عثمان حسين","halaqaId":"h11","grade":"","attendance":{}},
    {"id":"s148","serial":"148","name":"حمزة إيهاب سعيد","halaqaId":"h11","grade":"","attendance":{}},
    {"id":"s149","serial":"149","name":"عبد الرحمن محمود بديع","halaqaId":"h11","grade":"","attendance":{}},
    {"id":"s150","serial":"150","name":"عمار أحمد صالح","halaqaId":"h11","grade":"","attendance":{}},
    {"id":"s151","serial":"151","name":"خالد عبد الرحمن عبد الله","halaqaId":"h11","grade":"","attendance":{}},
    {"id":"s152","serial":"152","name":"تركي عبد العليم علي","halaqaId":"h11","grade":"","attendance":{}},
    {"id":"s153","serial":"153","name":"ريان صدام حميد","halaqaId":"h11","grade":"","attendance":{}},
    {"id":"s154","serial":"154","name":"مشاري محمد قحطان","halaqaId":"h11","grade":"","attendance":{}},
    {"id":"s155","serial":"155","name":"مصطفى بهاء","halaqaId":"h11","grade":"","attendance":{}},
    {"id":"s156","serial":"156","name":"أحمد إسحاق غنيدو","halaqaId":"h11","grade":"","attendance":{}},
    {"id":"s157","serial":"157","name":"مازن بكر","halaqaId":"h11","grade":"","attendance":{}},
    {"id":"s158","serial":"158","name":"عبد الإله حسين","halaqaId":"h11","grade":"","attendance":{}},
    {"id":"s159","serial":"159","name":"سامي شريف","halaqaId":"h11","grade":"","attendance":{}},
    {"id":"s160","serial":"160","name":"محمود سالم","halaqaId":"h11","grade":"","attendance":{}},
    {"id":"s161","serial":"161","name":"أكرم بشير","halaqaId":"h11","grade":"","attendance":{}},
    {"id":"s162","serial":"162","name":"أمجد تيسير كمال","halaqaId":"h12","grade":"","attendance":{}},
    {"id":"s163","serial":"163","name":"محمود ضياء السيد","halaqaId":"h12","grade":"","attendance":{}},
    {"id":"s164","serial":"164","name":"فهد عبد الله سعيد","halaqaId":"h12","grade":"","attendance":{}},
    {"id":"s165","serial":"165","name":"كرم هاني مهدي","halaqaId":"h12","grade":"","attendance":{}},
    {"id":"s166","serial":"166","name":"عمر محمد إبراهيم","halaqaId":"h12","grade":"","attendance":{}},
    {"id":"s167","serial":"167","name":"سيف سامي صالح","halaqaId":"h12","grade":"","attendance":{}},
    {"id":"s168","serial":"168","name":"عبد القادر ماهر جبر","halaqaId":"h12","grade":"","attendance":{}},
    {"id":"s169","serial":"169","name":"إياد عبد الرحمن صالح","halaqaId":"h12","grade":"","attendance":{}},
    {"id":"s170","serial":"170","name":"أحمد محمد إسماعيل","halaqaId":"h12","grade":"","attendance":{}},
    {"id":"s171","serial":"171","name":"جواد محمد أحمد","halaqaId":"h12","grade":"","attendance":{}},
    {"id":"s172","serial":"172","name":"مالك محمد","halaqaId":"h12","grade":"","attendance":{}},
    {"id":"s173","serial":"173","name":"عبد الجبار نبيل","halaqaId":"h12","grade":"","attendance":{}},
    {"id":"s174","serial":"174","name":"صالح محمد علي","halaqaId":"h12","grade":"","attendance":{}},
    {"id":"s175","serial":"175","name":"عبد العزيز نهار","halaqaId":"h12","grade":"","attendance":{}},
    {"id":"s176","serial":"176","name":"أحمد محمد قحطان","halaqaId":"h12","grade":"","attendance":{}},
    {"id":"s177","serial":"177","name":"عبد الله جميل","halaqaId":"h13","grade":"","attendance":{}},
    {"id":"s178","serial":"178","name":"عمار علاء أبو بكر","halaqaId":"h13","grade":"","attendance":{}},
    {"id":"s179","serial":"179","name":"عبد الرحمن أحمد عبد الفتاح","halaqaId":"h13","grade":"","attendance":{}},
    {"id":"s180","serial":"180","name":"كعب عبد الله","halaqaId":"h13","grade":"","attendance":{}},
    {"id":"s181","serial":"181","name":"موسى عبد الله","halaqaId":"h13","grade":"","attendance":{}},
    {"id":"s182","serial":"182","name":"غيث عبد الله سعيد","halaqaId":"h13","grade":"","attendance":{}},
    {"id":"s183","serial":"183","name":"محمد توفيق مطهر","halaqaId":"h13","grade":"","attendance":{}},
    {"id":"s184","serial":"184","name":"إياد محمد","halaqaId":"h13","grade":"","attendance":{}},
    {"id":"s185","serial":"185","name":"صالح مختار","halaqaId":"h13","grade":"","attendance":{}},
    {"id":"s186","serial":"186","name":"خالد مختار","halaqaId":"h13","grade":"","attendance":{}},
    {"id":"s187","serial":"187","name":"محمود أحمد السويري","halaqaId":"h13","grade":"","attendance":{}},
    {"id":"s188","serial":"188","name":"لؤي موفق","halaqaId":"h13","grade":"","attendance":{}},
    {"id":"s189","serial":"189","name":"حسين مختار","halaqaId":"h13","grade":"","attendance":{}},
    {"id":"s190","serial":"190","name":"مصطفى محمد علي","halaqaId":"h13","grade":"","attendance":{}},
    {"id":"s191","serial":"191","name":"عمار شريف","halaqaId":"h13","grade":"","attendance":{}},
    {"id":"s192","serial":"192","name":"محسن الذماري","halaqaId":"h13","grade":"","attendance":{}},
    {"id":"s193","serial":"193","name":"محمد الذماري","halaqaId":"h13","grade":"","attendance":{}},
    {"id":"s194","serial":"194","name":"عبد الله محمد","halaqaId":"h13","grade":"","attendance":{}},
    {"id":"s195","serial":"195","name":"طارق إسلام","halaqaId":"h13","grade":"","attendance":{}},
    {"id":"s196","serial":"196","name":"عبد الله المزا","halaqaId":"h13","grade":"","attendance":{}}
  ]
}
